LICENSE.txt
MANIFEST.in
README.rst
setup.cfg
setup.py
tests/__init__.py
tests/test_imports.py
tw2/__init__.py
tw2.jqplugins.flot.egg-info/PKG-INFO
tw2.jqplugins.flot.egg-info/SOURCES.txt
tw2.jqplugins.flot.egg-info/dependency_links.txt
tw2.jqplugins.flot.egg-info/entry_points.txt
tw2.jqplugins.flot.egg-info/namespace_packages.txt
tw2.jqplugins.flot.egg-info/not-zip-safe
tw2.jqplugins.flot.egg-info/requires.txt
tw2.jqplugins.flot.egg-info/top_level.txt
tw2/jqplugins/__init__.py
tw2/jqplugins/flot/__init__.py
tw2/jqplugins/flot/base.py
tw2/jqplugins/flot/defaults.py
tw2/jqplugins/flot/samples.py
tw2/jqplugins/flot/widgets.py
tw2/jqplugins/flot/static/jqplugins/flot/0.7/API.txt
tw2/jqplugins/flot/static/jqplugins/flot/0.7/FAQ.txt
tw2/jqplugins/flot/static/jqplugins/flot/0.7/LICENSE.txt
tw2/jqplugins/flot/static/jqplugins/flot/0.7/Makefile
tw2/jqplugins/flot/static/jqplugins/flot/0.7/NEWS.txt
tw2/jqplugins/flot/static/jqplugins/flot/0.7/PLUGINS.txt
tw2/jqplugins/flot/static/jqplugins/flot/0.7/README.txt
tw2/jqplugins/flot/static/jqplugins/flot/0.7/excanvas.js
tw2/jqplugins/flot/static/jqplugins/flot/0.7/excanvas.min.js
tw2/jqplugins/flot/static/jqplugins/flot/0.7/jquery.colorhelpers.js
tw2/jqplugins/flot/static/jqplugins/flot/0.7/jquery.colorhelpers.min.js
tw2/jqplugins/flot/static/jqplugins/flot/0.7/jquery.flot.crosshair.js
tw2/jqplugins/flot/static/jqplugins/flot/0.7/jquery.flot.crosshair.min.js
tw2/jqplugins/flot/static/jqplugins/flot/0.7/jquery.flot.fillbetween.js
tw2/jqplugins/flot/static/jqplugins/flot/0.7/jquery.flot.fillbetween.min.js
tw2/jqplugins/flot/static/jqplugins/flot/0.7/jquery.flot.image.js
tw2/jqplugins/flot/static/jqplugins/flot/0.7/jquery.flot.image.min.js
tw2/jqplugins/flot/static/jqplugins/flot/0.7/jquery.flot.js
tw2/jqplugins/flot/static/jqplugins/flot/0.7/jquery.flot.min.js
tw2/jqplugins/flot/static/jqplugins/flot/0.7/jquery.flot.navigate.js
tw2/jqplugins/flot/static/jqplugins/flot/0.7/jquery.flot.navigate.min.js
tw2/jqplugins/flot/static/jqplugins/flot/0.7/jquery.flot.pie.js
tw2/jqplugins/flot/static/jqplugins/flot/0.7/jquery.flot.pie.min.js
tw2/jqplugins/flot/static/jqplugins/flot/0.7/jquery.flot.resize.js
tw2/jqplugins/flot/static/jqplugins/flot/0.7/jquery.flot.resize.min.js
tw2/jqplugins/flot/static/jqplugins/flot/0.7/jquery.flot.selection.js
